{
     "data" : [
  {
    "name": "New Year",
    "createdDate": "01 Jan 2025",
    "days": "Monday"
  },
  {
    "name": "World Braille Day",
    "createdDate": "04 Jan 2025",
    "days": "Saturday"
  },
  {
    "name": "Republic Day of India",
    "createdDate": "26 Jan 2025",
    "days": "Sunday"
  },
  {
    "name": "World Cancer Day",
    "createdDate": "04 Feb 2025",
    "days": "Tuesday"
  },
  {
    "name": "World Birth Defects Day",
    "createdDate": "03 Mar 2025",
    "days": "Saturday"
  },
  {
    "name": "International Women's Day",
    "createdDate": "08 May 2025",
    "days": "Saturday"
  },
  {
    "name": "Good Friday",
    "createdDate": "29 Mar 2025",
    "days": "Friday"
  },
  {
    "name": "Easter Monday",
    "createdDate": "01 Apr 2025",
    "days": "Tuesday"
  },
  {
    "name": "May Day",
    "createdDate": "01 May 2025",
    "days": "Thursday"
  },
  {
    "name": "Memorial Day",
    "createdDate": "27 May 2025",
    "days": "Tuesday"
  }
],
"totalData":10
}